firstProject/Perceptron.py
firstProject/__init__.py
firstProject_rinki-0.0.3.dist-info/LICENSE
firstProject_rinki-0.0.3.dist-info/METADATA
firstProject_rinki-0.0.3.dist-info/WHEEL
firstProject_rinki-0.0.3.dist-info/top_level.txt
firstProject_rinki-0.0.3.dist-info/RECORD
