Metadata-Version: 2.1
Name: firstProject-rinki
Version: 0.0.3
Summary: A small package for perceptron
Home-page: https://github.com/rinki/First Project
Author: rinki
Author-email: rinki.sharma@gmail.com
Project-URL: Bug Tracker, https://github.com/rinki/First Project/issues
Classifier: Programming Language :: Python :: 3
Classifier: License :: OSI Approved :: MIT License
Classifier: Operating System :: OS Independent
Requires-Python: >=3.6
License-File: LICENSE
Requires-Dist: numpy (==1.19.5)
Requires-Dist: pandas (==1.3.4)
Requires-Dist: joblib (==1.1.0)
